{
  "cluster_id": "394019",
  "tft_set": "TFTSet16",
  "units": [
    "费德提克",
    "卢锡安与赛娜",
    "厄运小姐",
    "诺提勒斯",
    "奥恩",
    "希瓦娜",
    "塔姆",
    "塔里克",
    "孙悟空"
  ],
  "traits": [
    "比尔吉沃特 (1)",
    "山隐之焰 (1)",
    "斗士 (1)",
    "河流之王 (1)",
    "枪手 (1)",
    "远古恐惧 (1)",
    "主宰 (1)",
    "龙血武姬 (1)",
    "系魂圣枪 (1)",
    "巨神峰 (1)",
    "神盾使 (1)"
  ],
  "stars": [],
  "name_string": "TFT16_Bilgewater, TFT16_MissFortune, TFT16_Wukong",
  "display_names": [
    {
      "name": "比尔吉沃特",
      "type": "trait",
      "score": 1.4774218313791179
    },
    {
      "name": "厄运小姐",
      "type": "unit",
      "score": 4.155517169179229
    },
    {
      "name": "塔姆",
      "type": "unit",
      "score": 3.457757537688442
    }
  ],
  "count": 40318,
  "avg_placement": 4.1515,
  "top4_rate": 0.5553,
  "win_rate": 0.1737,
  "tier": "S",
  "builds": [
    {
      "unit": "厄运小姐",
      "items": [
        "亡者的短剑",
        "大副的燧发枪",
        "朔极之矛"
      ],
      "avg_placement": 3.3676,
      "count": 672,
      "score": 0.6074,
      "place_change": -0.809,
      "priority_scores": {
        "亡者的短剑": 100,
        "大副的燧发枪": 85,
        "朔极之矛": 72
      }
    },
    {
      "unit": "塔姆",
      "items": [
        "酒吧指虎",
        "成堆柑橘",
        "圣盾使的誓约"
      ],
      "avg_placement": 3.1673,
      "count": 526,
      "score": 0.5164,
      "place_change": -1.01,
      "priority_scores": {
        "酒吧指虎": 100,
        "成堆柑橘": 85,
        "圣盾使的誓约": 72
      }
    },
    {
      "unit": "卢锡安与赛娜",
      "items": [
        "最后的轻语",
        "红霸符",
        "朔极之矛"
      ],
      "avg_placement": 3.3045,
      "count": 1156,
      "score": 0.3841,
      "place_change": -0.872,
      "priority_scores": {
        "最后的轻语": 100,
        "红霸符": 85,
        "朔极之矛": 72
      }
    },
    {
      "unit": "孙悟空",
      "items": [
        "石像鬼石板甲",
        "薄暮法袍",
        "狂徒铠甲"
      ],
      "avg_placement": 3.9551,
      "count": 89,
      "score": 0.1077,
      "place_change": -0.222,
      "priority_scores": {
        "石像鬼石板甲": 100,
        "薄暮法袍": 85,
        "狂徒铠甲": 72
      }
    }
  ],
  "build_items": {
    "朔极之矛": {
      "itemNames": "TFT_Item_SpearOfShojin",
      "count": 24977,
      "avg": 3.9878,
      "pcnt": 0.87162
    },
    "最后的轻语": {
      "itemNames": "TFT_Item_LastWhisper",
      "count": 14157,
      "avg": 4.0078,
      "pcnt": 0.49403
    },
    "圣盾使的誓约": {
      "itemNames": "TFT_Item_FrozenHeart",
      "count": 13157,
      "avg": 3.8168,
      "pcnt": 0.45914
    },
    "石像鬼石板甲": {
      "itemNames": "TFT_Item_GargoyleStoneplate",
      "count": 13150,
      "avg": 3.9886,
      "pcnt": 0.45889
    },
    "狂徒铠甲": {
      "itemNames": "TFT_Item_WarmogsArmor",
      "count": 11336,
      "avg": 3.8798,
      "pcnt": 0.39559
    },
    "薄暮法袍": {
      "itemNames": "TFT_Item_SpectralGauntlet",
      "count": 10790,
      "avg": 3.8567,
      "pcnt": 0.37654
    },
    "成堆柑橘": {
      "itemNames": "TFT16_Item_Bilgewater_PileOCitrus",
      "count": 9251,
      "avg": 3.637,
      "pcnt": 0.32283
    },
    "红霸符": {
      "itemNames": "TFT_Item_RapidFireCannon",
      "count": 9027,
      "avg": 3.8578,
      "pcnt": 0.31501
    },
    "大副的燧发枪": {
      "itemNames": "TFT16_Item_Bilgewater_FirstMatesFlintlock",
      "count": 8621,
      "avg": 3.7532,
      "pcnt": 0.30084
    },
    "亡者的短剑": {
      "itemNames": "TFT16_Item_Bilgewater_DeadmansDagger",
      "count": 7738,
      "avg": 3.875,
      "pcnt": 0.27003
    },
    "酒吧指虎": {
      "itemNames": "TFT16_Item_Bilgewater_FreebootersFrock",
      "count": 7041,
      "avg": 3.6476,
      "pcnt": 0.24571
    }
  },
  "trends": [
    {
      "day": "2026-04-07",
      "count": 7661,
      "avg": 4.1921,
      "pick_rate": 0.00994
    },
    {
      "day": "2026-04-08",
      "count": 10633,
      "avg": 4.1857,
      "pick_rate": 0.009727
    },
    {
      "day": "2026-04-09",
      "count": 10416,
      "avg": 4.1429,
      "pick_rate": 0.00967
    },
    {
      "day": "2026-04-10",
      "count": 10217,
      "avg": 4.237,
      "pick_rate": 0.009687
    },
    {
      "day": "2026-04-11",
      "count": 10438,
      "avg": 4.1989,
      "pick_rate": 0.00971
    },
    {
      "day": "2026-04-12",
      "count": 10419,
      "avg": 4.1468,
      "pick_rate": 0.009728
    },
    {
      "day": "2026-04-13",
      "count": 9018,
      "avg": 4.1911,
      "pick_rate": 0.009684
    },
    {
      "day": "2026-04-14",
      "count": 2337,
      "avg": 4.1553,
      "pick_rate": 0.009235
    }
  ],
  "levelling": "Fast 9",
  "difficulty": -0.024
}
