{
  "cluster_id": "394064",
  "tft_set": "TFTSet16",
  "units": [
    "加里奥",
    "盖伦",
    "嘉文四世",
    "拉克丝",
    "波比",
    "娑娜",
    "斯维因",
    "赵信",
    "基兰"
  ],
  "traits": [
    "时光守护者 (1)",
    "护卫 (1)",
    "德玛西亚 (3)",
    "正义巨像 (1)",
    "神谕者 (1)",
    "主宰 (1)",
    "法师 (1)"
  ],
  "stars": [
    "嘉文四世",
    "娑娜",
    "艾尼维亚",
    "厄斐琉斯",
    "兰博",
    "巴德",
    "克格莫",
    "凯特琳"
  ],
  "name_string": "TFT16_Demacia, TFT16_JarvanIV",
  "display_names": [
    {
      "name": "德玛西亚",
      "type": "trait",
      "score": 1.9685366032748366
    },
    {
      "name": "嘉文四世",
      "type": "unit",
      "score": 2.700804023790293
    }
  ],
  "count": 7184,
  "avg_placement": 6.1148,
  "top4_rate": 0.2226,
  "win_rate": 0.031,
  "tier": "D",
  "builds": [
    {
      "unit": "嘉文四世",
      "items": [
        "巨龙之爪",
        "日炎斗篷",
        "振奋盔甲"
      ],
      "avg_placement": 4.9058,
      "count": 223,
      "score": 0.418,
      "place_change": -1.311,
      "priority_scores": {
        "巨龙之爪": 100,
        "日炎斗篷": 85,
        "振奋盔甲": 72
      }
    },
    {
      "unit": "娑娜",
      "items": [
        "珠光护手",
        "纳什之牙",
        "纳什之牙"
      ],
      "avg_placement": 5.2466,
      "count": 665,
      "score": 0.3065,
      "place_change": -0.971,
      "priority_scores": {
        "珠光护手": 100,
        "纳什之牙": 72
      }
    },
    {
      "unit": "拉克丝",
      "items": [
        "珠光护手",
        "灭世者的死亡之帽",
        "朔极之矛"
      ],
      "avg_placement": 4.9688,
      "count": 96,
      "score": 0.161,
      "place_change": -1.248,
      "priority_scores": {
        "珠光护手": 100,
        "灭世者的死亡之帽": 85,
        "朔极之矛": 72
      }
    },
    {
      "unit": "薇恩",
      "items": [
        "鬼索的狂暴之刃",
        "无尽之刃",
        "海妖之怒"
      ],
      "avg_placement": 5.6614,
      "count": 319,
      "score": 0.0778,
      "place_change": -0.556,
      "priority_scores": {
        "鬼索的狂暴之刃": 100,
        "无尽之刃": 85,
        "海妖之怒": 72
      }
    }
  ],
  "build_items": {
    "珠光护手": {
      "itemNames": "珠光护手",
      "count": 17803,
      "avg": 5.8539,
      "pcnt": 0.65361
    },
    "朔极之矛": {
      "itemNames": "朔极之矛",
      "count": 12561,
      "avg": 5.9778,
      "pcnt": 0.46116
    },
    "纳什之牙": {
      "itemNames": "纳什之牙",
      "count": 11342,
      "avg": 5.7791,
      "pcnt": 0.4164
    },
    "日炎斗篷": {
      "itemNames": "日炎斗篷",
      "count": 9626,
      "avg": 5.702,
      "pcnt": 0.3534
    },
    "振奋盔甲": {
      "itemNames": "振奋盔甲",
      "count": 8536,
      "avg": 5.6946,
      "pcnt": 0.31339
    },
    "巨龙之爪": {
      "itemNames": "巨龙之爪",
      "count": 8511,
      "avg": 5.7092,
      "pcnt": 0.31247
    },
    "鬼索的狂暴之刃": {
      "itemNames": "鬼索的狂暴之刃",
      "count": 8237,
      "avg": 5.706,
      "pcnt": 0.30241
    },
    "无尽之刃": {
      "itemNames": "无尽之刃",
      "count": 5139,
      "avg": 5.5958,
      "pcnt": 0.18867
    },
    "海妖之怒": {
      "itemNames": "海妖之怒",
      "count": 4658,
      "avg": 5.8295,
      "pcnt": 0.17101
    },
    "灭世者的死亡之帽": {
      "itemNames": "灭世者的死亡之帽",
      "count": 3344,
      "avg": 5.4094,
      "pcnt": 0.12277
    }
  },
  "trends": [
    {
      "day": "2026-03-17",
      "count": 5017,
      "avg": 6.233,
      "pick_rate": 0.00504
    },
    {
      "day": "2026-03-18",
      "count": 9260,
      "avg": 6.2243,
      "pick_rate": 0.00511
    },
    {
      "day": "2026-03-19",
      "count": 9125,
      "avg": 6.2323,
      "pick_rate": 0.004988
    },
    {
      "day": "2026-03-20",
      "count": 9718,
      "avg": 6.2052,
      "pick_rate": 0.005213
    },
    {
      "day": "2026-03-21",
      "count": 10022,
      "avg": 6.1905,
      "pick_rate": 0.005144
    },
    {
      "day": "2026-03-22",
      "count": 9528,
      "avg": 6.2583,
      "pick_rate": 0.004841
    },
    {
      "day": "2026-03-23",
      "count": 8934,
      "avg": 6.1951,
      "pick_rate": 0.004876
    },
    {
      "day": "2026-03-24",
      "count": 2985,
      "avg": 6.2291,
      "pick_rate": 0.004765
    }
  ],
  "levelling": "lvl 5",
  "difficulty": -0.217
}