{
  "cluster_id": "394049",
  "tft_set": "TFTSet16",
  "units": [
    "加里奥",
    "盖伦",
    "嘉文四世",
    "拉克丝",
    "波比",
    "娑娜",
    "斯维因",
    "塔里克",
    "赵信",
    "基兰"
  ],
  "traits": [
    "时光守护者 (1)",
    "护卫 (1)",
    "德玛西亚 (3)",
    "正义巨像 (1)",
    "神谕者 (1)",
    "主宰 (1)",
    "法师 (1)",
    "巨神峰 (1)"
  ],
  "stars": [
    "厄斐琉斯"
  ],
  "name_string": "TFT16_Demacia, TFT16_Lux, TFT16_Poppy",
  "display_names": [
    {
      "name": "德玛西亚",
      "type": "trait",
      "score": 2.5182964439917948
    },
    {
      "name": "拉克丝",
      "type": "unit",
      "score": 4.077087487269233
    }
  ],
  "count": 129533,
  "avg_placement": 4.6104,
  "top4_rate": 0.4818,
  "win_rate": 0.1009,
  "tier": "B",
  "builds": [
    {
      "unit": "拉克丝",
      "items": [
        "海克斯科技枪刃",
        "珠光护手",
        "纳什之牙"
      ],
      "avg_placement": 4.0624,
      "count": 4054,
      "score": 0.629,
      "place_change": -0.754,
      "priority_scores": {
        "海克斯科技枪刃": 100,
        "珠光护手": 85,
        "纳什之牙": 72
      }
    },
    {
      "unit": "盖伦",
      "items": [
        "棘刺背心",
        "巨龙之爪",
        "振奋盔甲"
      ],
      "avg_placement": 4.1683,
      "count": 3649,
      "score": 0.4879,
      "place_change": -0.648,
      "priority_scores": {
        "棘刺背心": 100,
        "巨龙之爪": 85,
        "振奋盔甲": 72
      }
    },
    {
      "unit": "基兰",
      "items": [
        "莫雷洛秘典",
        "朔极之矛",
        "虚空之杖"
      ],
      "avg_placement": 2.9544,
      "count": 701,
      "score": 0.1821,
      "place_change": -1.862,
      "priority_scores": {
        "莫雷洛秘典": 100,
        "朔极之矛": 85,
        "虚空之杖": 72
      }
    },
    {
      "unit": "斯维因",
      "items": [
        "德玛西亚纹章",
        "圣盾使的誓约"
      ],
      "avg_placement": 4.0313,
      "count": 128,
      "score": 0.0142,
      "place_change": -0.785,
      "priority_scores": {
        "德玛西亚纹章": 100,
        "圣盾使的誓约": 85
      }
    },
    {
      "unit": "加里奥",
      "items": [
        "巨龙之爪"
      ],
      "avg_placement": 4.1841,
      "count": 929,
      "score": 0.0124,
      "place_change": -0.633,
      "priority_scores": {
        "巨龙之爪": 100
      }
    }
  ],
  "build_items": {
    "珠光护手": {
      "itemNames": "TFT_Item_JeweledGauntlet",
      "count": 66421,
      "avg": 4.7332,
      "pcnt": 0.95278
    },
    "朔极之矛": {
      "itemNames": "TFT_Item_SpearOfShojin",
      "count": 48800,
      "avg": 4.7277,
      "pcnt": 0.70001
    },
    "纳什之牙": {
      "itemNames": "TFT_Item_Leviathan",
      "count": 45133,
      "avg": 4.7352,
      "pcnt": 0.64741
    },
    "巨龙之爪": {
      "itemNames": "TFT_Item_DragonsClaw",
      "count": 36631,
      "avg": 4.5175,
      "pcnt": 0.52545
    },
    "振奋盔甲": {
      "itemNames": "TFT_Item_Redemption",
      "count": 32382,
      "avg": 4.3991,
      "pcnt": 0.4645
    },
    "虚空之杖": {
      "itemNames": "TFT_Item_StatikkShiv",
      "count": 27561,
      "avg": 4.6548,
      "pcnt": 0.39535
    },
    "棘刺背心": {
      "itemNames": "TFT_Item_BrambleVest",
      "count": 25133,
      "avg": 4.6123,
      "pcnt": 0.36052
    },
    "海克斯科技枪刃": {
      "itemNames": "TFT_Item_HextechGunblade",
      "count": 23669,
      "avg": 4.3156,
      "pcnt": 0.33952
    },
    "德玛西亚纹章": {
      "itemNames": "TFT16_Item_DemaciaEmblemItem",
      "count": 15306,
      "avg": 4.3954,
      "pcnt": 0.21956
    },
    "圣盾使的誓约": {
      "itemNames": "TFT_Item_FrozenHeart",
      "count": 11137,
      "avg": 4.0747,
      "pcnt": 0.15975
    },
    "莫雷洛秘典": {
      "itemNames": "TFT_Item_Morellonomicon",
      "count": 9121,
      "avg": 4.0049,
      "pcnt": 0.13084
    }
  },
  "trends": [
    {
      "day": "2026-04-07",
      "count": 17348,
      "avg": 4.8748,
      "pick_rate": 0.022508
    },
    {
      "day": "2026-04-08",
      "count": 25069,
      "avg": 4.8581,
      "pick_rate": 0.022932
    },
    {
      "day": "2026-04-09",
      "count": 24729,
      "avg": 4.8266,
      "pick_rate": 0.022958
    },
    {
      "day": "2026-04-10",
      "count": 24631,
      "avg": 4.8446,
      "pick_rate": 0.023352
    },
    {
      "day": "2026-04-11",
      "count": 25328,
      "avg": 4.8001,
      "pick_rate": 0.023562
    },
    {
      "day": "2026-04-12",
      "count": 25295,
      "avg": 4.8212,
      "pick_rate": 0.023617
    },
    {
      "day": "2026-04-13",
      "count": 21930,
      "avg": 4.8363,
      "pick_rate": 0.02355
    },
    {
      "day": "2026-04-14",
      "count": 5997,
      "avg": 4.8057,
      "pick_rate": 0.023697
    }
  ],
  "levelling": "Fast 8",
  "difficulty": -0.048
}
