{
  "cluster_id": "394009",
  "tft_set": "TFTSet16",
  "units": [
    "安蓓萨",
    "德莱文",
    "费德提克",
    "千珏",
    "卢锡安与赛娜",
    "希瓦娜",
    "斯卡纳",
    "斯维因",
    "塔里克"
  ],
  "traits": [
    "远古恐惧 (1)",
    "主宰 (1)",
    "永猎双子 (1)",
    "诺克萨斯 (1)",
    "迅击战士 (1)",
    "龙血武姬 (1)",
    "系魂圣枪 (1)",
    "巨神峰 (1)",
    "征服者 (1)"
  ],
  "stars": [],
  "name_string": "TFT16_Noxus, TFT16_Skarner",
  "display_names": [
    {
      "name": "诺克萨斯",
      "type": "trait",
      "score": 0.9749187107364965
    },
    {
      "name": "千珏",
      "type": "unit",
      "score": 3.577516810304006
    }
  ],
  "count": 20167,
  "avg_placement": 4.1962,
  "top4_rate": 0.541,
  "win_rate": 0.1972,
  "tier": "S",
  "builds": [
    {
      "unit": "千珏",
      "items": [
        "鬼索的狂暴之刃",
        "巨人杀手",
        "海妖之怒"
      ],
      "avg_placement": 3.5354,
      "count": 15311,
      "score": 0.6408,
      "place_change": -0.75,
      "priority_scores": {
        "鬼索的狂暴之刃": 100,
        "巨人杀手": 85,
        "海妖之怒": 72
      }
    },
    {
      "unit": "卢锡安与赛娜",
      "items": [
        "最后的轻语",
        "红霸符",
        "朔极之矛"
      ],
      "avg_placement": 3.0181,
      "count": 1270,
      "score": 0.2994,
      "place_change": -1.267,
      "priority_scores": {
        "最后的轻语": 100,
        "红霸符": 85,
        "朔极之矛": 72
      }
    },
    {
      "unit": "斯卡纳",
      "items": [
        "日炎斗篷",
        "振奋盔甲",
        "薄暮法袍"
      ],
      "avg_placement": 3.8252,
      "count": 2866,
      "score": 0.274,
      "place_change": -0.46,
      "priority_scores": {
        "日炎斗篷": 100,
        "振奋盔甲": 85,
        "薄暮法袍": 72
      }
    },
    {
      "unit": "希瓦娜",
      "items": [
        "饮血剑",
        "斯特拉克的挑战护手",
        "泰坦的坚决"
      ],
      "avg_placement": 3.2407,
      "count": 1155,
      "score": 0.0902,
      "place_change": -1.044,
      "priority_scores": {
        "饮血剑": 100,
        "斯特拉克的挑战护手": 85,
        "泰坦的坚决": 72
      }
    }
  ],
  "build_items": {
    "鬼索的狂暴之刃": {
      "itemNames": "鬼索的狂暴之刃",
      "count": 134849,
      "avg": 4.1746,
      "pcnt": 1.06425
    },
    "海妖之怒": {
      "itemNames": "海妖之怒",
      "count": 74149,
      "avg": 4.0262,
      "pcnt": 0.5852
    },
    "日炎斗篷": {
      "itemNames": "日炎斗篷",
      "count": 66949,
      "avg": 4.0827,
      "pcnt": 0.52837
    },
    "振奋盔甲": {
      "itemNames": "振奋盔甲",
      "count": 65552,
      "avg": 4.1596,
      "pcnt": 0.51735
    },
    "巨人杀手": {
      "itemNames": "巨人杀手",
      "count": 52848,
      "avg": 3.932,
      "pcnt": 0.41708
    },
    "朔极之矛": {
      "itemNames": "朔极之矛",
      "count": 52609,
      "avg": 4.0234,
      "pcnt": 0.4152
    },
    "最后的轻语": {
      "itemNames": "最后的轻语",
      "count": 42038,
      "avg": 3.8897,
      "pcnt": 0.33177
    },
    "薄暮法袍": {
      "itemNames": "薄暮法袍",
      "count": 36912,
      "avg": 3.8651,
      "pcnt": 0.29132
    },
    "饮血剑": {
      "itemNames": "饮血剑",
      "count": 30622,
      "avg": 3.8281,
      "pcnt": 0.24167
    },
    "泰坦的坚决": {
      "itemNames": "泰坦的坚决",
      "count": 21372,
      "avg": 3.7728,
      "pcnt": 0.16867
    },
    "红霸符": {
      "itemNames": "红霸符",
      "count": 20876,
      "avg": 3.7561,
      "pcnt": 0.16476
    },
    "斯特拉克的挑战护手": {
      "itemNames": "斯特拉克的挑战护手",
      "count": 20064,
      "avg": 3.6473,
      "pcnt": 0.15835
    }
  },
  "trends": [
    {
      "day": "2026-03-17",
      "count": 24402,
      "avg": 4.1742,
      "pick_rate": 0.024515
    },
    {
      "day": "2026-03-18",
      "count": 45568,
      "avg": 4.1916,
      "pick_rate": 0.025147
    },
    {
      "day": "2026-03-19",
      "count": 43795,
      "avg": 4.2351,
      "pick_rate": 0.023938
    },
    {
      "day": "2026-03-20",
      "count": 43080,
      "avg": 4.2525,
      "pick_rate": 0.023108
    },
    {
      "day": "2026-03-21",
      "count": 45045,
      "avg": 4.2664,
      "pick_rate": 0.023121
    },
    {
      "day": "2026-03-22",
      "count": 44786,
      "avg": 4.2938,
      "pick_rate": 0.022753
    },
    {
      "day": "2026-03-23",
      "count": 40958,
      "avg": 4.3007,
      "pick_rate": 0.022352
    },
    {
      "day": "2026-03-24",
      "count": 14873,
      "avg": 4.2406,
      "pick_rate": 0.023741
    }
  ],
  "levelling": "Fast 9",
  "difficulty": 0.026
}