{
  "name": "巴德",
  "appear_in_comps": [
    {
      "cluster_id": "592dcf64a8965208bbaf01de0393a109",
      "comp_name": "木灵族霞",
      "tier": "S",
      "avg_placement": 2.88
    },
    {
      "cluster_id": "b649d1eee8f7019800b2b8f50811534a",
      "comp_name": "重装战士薇古丝",
      "tier": "S",
      "avg_placement": 3.69
    }
  ],
  "builds": [
    {
      "cluster_id": "b649d1eee8f7019800b2b8f50811534a",
      "comp_name": "重装战士薇古丝",
      "items": [
        "莫雷洛秘典",
        "朔极之矛",
        "虚空之杖"
      ],
      "avg_placement": 3.69,
      "count": 35701,
      "priority_scores": {
        "莫雷洛秘典": 80,
        "朔极之矛": 80,
        "虚空之杖": 80
      }
    }
  ]
}
